Workbook
Name lst_Clientes: _Listas!$C$2:$C$481
Name lst_Industrias: _Listas!$B$2:$B$16
Name lst_Setores: _Listas!$A$2:$A$11

Sheet Capa - Dashboard
E2: CRM 3MV REPRESENTAÇÃO
E5: Base de Clientes & Indústrias
B7: Atualizado via API Suas Vendas · Dados manuais preservados entre execuções
B9: 502 | D9: 189 | F9: 15 | H9: 42
B10: Clientes na base | D10: Clientes ATIVOS | F10: Indústrias ATIVAS | H10: Grupos / redes
B13: ◆ BUSCAR CONTATO DE INDÚSTRIA
B15: Indústria: | I15: =HYPERLINK("#'Capa - Dashboard'!C15","🗑 Limpar (clique e tecle Delete)") -> 🗑 Limpar (clique e tecle Delete)
B17: Contatos por setor da indústria escolhida:
B18: Setor | C18: Contato | E18: E-mail | H18: Telefone
B19: Financeiro | C19: =IFERROR(IF(VLOOKUP($C$15,'CRM Indústrias'!$B:$XFD,MATCH("Financeiro — contato",'CRM Indústrias'!$B$1:$XFD$1,0),FALSE)=0,"",VLOOKUP($C$15,'CRM Indústrias'!$B:$XFD,MATCH("Financeiro — contato",'CRM Indústrias'!$B$1:$XFD$1,0),FALSE)),"") | E19: =IFERROR(IF(VLOOKUP($C$15,'CRM Indústrias'!$B:$XFD,MATCH("Financeiro — e-mail",'CRM Indústrias'!$B$1:$XFD$1,0),FALSE)=0,"",VLOOKUP($C$15,'CRM Indústrias'!$B:$XFD,MATCH("Financeiro — e-mail",'CRM Indústrias'!$B$1:$XFD$1,0),FALSE)),"") | H19: =IFERROR(IF(VLOOKUP($C$15,'CRM Indústrias'!$B:$XFD,MATCH("Financeiro — telefone",'CRM Indústrias'!$B$1:$XFD$1,0),FALSE)=0,"",VLOOKUP($C$15,'CRM Indústrias'!$B:$XFD,MATCH("Financeiro — telefone",'CRM Indústrias'!$B$1:$XFD$1,0),FALSE)),"")
B20: Contas a Pagar | C20: =IFERROR(IF(VLOOKUP($C$15,'CRM Indústrias'!$B:$XFD,MATCH("Contas a Pagar — contato",'CRM Indústrias'!$B$1:$XFD$1,0),FALSE)=0,"",VLOOKUP($C$15,'CRM Indústrias'!$B:$XFD,MATCH("Contas a Pagar — contato",'CRM Indústrias'!$B$1:$XFD$1,0),FALSE)),"") | E20: =IFERROR(IF(VLOOKUP($C$15,'CRM Indústrias'!$B:$XFD,MATCH("Contas a Pagar — e-mail",'CRM Indústrias'!$B$1:$XFD$1,0),FALSE)=0,"",VLOOKUP($C$15,'CRM Indústrias'!$B:$XFD,MATCH("Contas a Pagar — e-mail",'CRM Indústrias'!$B$1:$XFD$1,0),FALSE)),"") | H20: =IFERROR(IF(VLOOKUP($C$15,'CRM Indústrias'!$B:$XFD,MATCH("Contas a Pagar — telefone",'CRM Indústrias'!$B$1:$XFD$1,0),FALSE)=0,"",VLOOKUP($C$15,'CRM Indústrias'!$B:$XFD,MATCH("Contas a Pagar — telefone",'CRM Indústrias'!$B$1:$XFD$1,0),FALSE)),"")
B21: Contas a Receber | C21: =IFERROR(IF(VLOOKUP($C$15,'CRM Indústrias'!$B:$XFD,MATCH("Contas a Receber — contato",'CRM Indústrias'!$B$1:$XFD$1,0),FALSE)=0,"",VLOOKUP($C$15,'CRM Indústrias'!$B:$XFD,MATCH("Contas a Receber — contato",'CRM Indústrias'!$B$1:$XFD$1,0),FALSE)),"") | E21: =IFERROR(IF(VLOOKUP($C$15,'CRM Indústrias'!$B:$XFD,MATCH("Contas a Receber — e-mail",'CRM Indústrias'!$B$1:$XFD$1,0),FALSE)=0,"",VLOOKUP($C$15,'CRM Indústrias'!$B:$XFD,MATCH("Contas a Receber — e-mail",'CRM Indústrias'!$B$1:$XFD$1,0),FALSE)),"") | H21: =IFERROR(IF(VLOOKUP($C$15,'CRM Indústrias'!$B:$XFD,MATCH("Contas a Receber — telefone",'CRM Indústrias'!$B$1:$XFD$1,0),FALSE)=0,"",VLOOKUP($C$15,'CRM Indústrias'!$B:$XFD,MATCH("Contas a Receber — telefone",'CRM Indústrias'!$B$1:$XFD$1,0),FALSE)),"")
B22: Marketing | C22: =IFERROR(IF(VLOOKUP($C$15,'CRM Indústrias'!$B:$XFD,MATCH("Marketing — contato",'CRM Indústrias'!$B$1:$XFD$1,0),FALSE)=0,"",VLOOKUP($C$15,'CRM Indústrias'!$B:$XFD,MATCH("Marketing — contato",'CRM Indústrias'!$B$1:$XFD$1,0),FALSE)),"") | E22: =IFERROR(IF(VLOOKUP($C$15,'CRM Indústrias'!$B:$XFD,MATCH("Marketing — e-mail",'CRM Indústrias'!$B$1:$XFD$1,0),FALSE)=0,"",VLOOKUP($C$15,'CRM Indústrias'!$B:$XFD,MATCH("Marketing — e-mail",'CRM Indústrias'!$B$1:$XFD$1,0),FALSE)),"") | H22: =IFERROR(IF(VLOOKUP($C$15,'CRM Indústrias'!$B:$XFD,MATCH("Marketing — telefone",'CRM Indústrias'!$B$1:$XFD$1,0),FALSE)=0,"",VLOOKUP($C$15,'CRM Indústrias'!$B:$XFD,MATCH("Marketing — telefone",'CRM Indústrias'!$B$1:$XFD$1,0),FALSE)),"")
B23: ADM | C23: =IFERROR(IF(VLOOKUP($C$15,'CRM Indústrias'!$B:$XFD,MATCH("ADM — contato",'CRM Indústrias'!$B$1:$XFD$1,0),FALSE)=0,"",VLOOKUP($C$15,'CRM Indústrias'!$B:$XFD,MATCH("ADM — contato",'CRM Indústrias'!$B$1:$XFD$1,0),FALSE)),"") | E23: =IFERROR(IF(VLOOKUP($C$15,'CRM Indústrias'!$B:$XFD,MATCH("ADM — e-mail",'CRM Indústrias'!$B$1:$XFD$1,0),FALSE)=0,"",VLOOKUP($C$15,'CRM Indústrias'!$B:$XFD,MATCH("ADM — e-mail",'CRM Indústrias'!$B$1:$XFD$1,0),FALSE)),"") | H23: =IFERROR(IF(VLOOKUP($C$15,'CRM Indústrias'!$B:$XFD,MATCH("ADM — telefone",'CRM Indústrias'!$B$1:$XFD$1,0),FALSE)=0,"",VLOOKUP($C$15,'CRM Indústrias'!$B:$XFD,MATCH("ADM — telefone",'CRM Indústrias'!$B$1:$XFD$1,0),FALSE)),"")
B24: Gerência | C24: =IFERROR(IF(VLOOKUP($C$15,'CRM Indústrias'!$B:$XFD,MATCH("Gerência — contato",'CRM Indústrias'!$B$1:$XFD$1,0),FALSE)=0,"",VLOOKUP($C$15,'CRM Indústrias'!$B:$XFD,MATCH("Gerência — contato",'CRM Indústrias'!$B$1:$XFD$1,0),FALSE)),"") | E24: =IFERROR(IF(VLOOKUP($C$15,'CRM Indústrias'!$B:$XFD,MATCH("Gerência — e-mail",'CRM Indústrias'!$B$1:$XFD$1,0),FALSE)=0,"",VLOOKUP($C$15,'CRM Indústrias'!$B:$XFD,MATCH("Gerência — e-mail",'CRM Indústrias'!$B$1:$XFD$1,0),FALSE)),"") | H24: =IFERROR(IF(VLOOKUP($C$15,'CRM Indústrias'!$B:$XFD,MATCH("Gerência — telefone",'CRM Indústrias'!$B$1:$XFD$1,0),FALSE)=0,"",VLOOKUP($C$15,'CRM Indústrias'!$B:$XFD,MATCH("Gerência — telefone",'CRM Indústrias'!$B$1:$XFD$1,0),FALSE)),"")
B25: Supervisão | C25: =IFERROR(IF(VLOOKUP($C$15,'CRM Indústrias'!$B:$XFD,MATCH("Supervisão — contato",'CRM Indústrias'!$B$1:$XFD$1,0),FALSE)=0,"",VLOOKUP($C$15,'CRM Indústrias'!$B:$XFD,MATCH("Supervisão — contato",'CRM Indústrias'!$B$1:$XFD$1,0),FALSE)),"") | E25: =IFERROR(IF(VLOOKUP($C$15,'CRM Indústrias'!$B:$XFD,MATCH("Supervisão — e-mail",'CRM Indústrias'!$B$1:$XFD$1,0),FALSE)=0,"",VLOOKUP($C$15,'CRM Indústrias'!$B:$XFD,MATCH("Supervisão — e-mail",'CRM Indústrias'!$B$1:$XFD$1,0),FALSE)),"") | H25: =IFERROR(IF(VLOOKUP($C$15,'CRM Indústrias'!$B:$XFD,MATCH("Supervisão — telefone",'CRM Indústrias'!$B$1:$XFD$1,0),FALSE)=0,"",VLOOKUP($C$15,'CRM Indústrias'!$B:$XFD,MATCH("Supervisão — telefone",'CRM Indústrias'!$B$1:$XFD$1,0),FALSE)),"")
B26: Trocas | C26: =IFERROR(IF(VLOOKUP($C$15,'CRM Indústrias'!$B:$XFD,MATCH("Trocas — contato",'CRM Indústrias'!$B$1:$XFD$1,0),FALSE)=0,"",VLOOKUP($C$15,'CRM Indústrias'!$B:$XFD,MATCH("Trocas — contato",'CRM Indústrias'!$B$1:$XFD$1,0),FALSE)),"") | E26: =IFERROR(IF(VLOOKUP($C$15,'CRM Indústrias'!$B:$XFD,MATCH("Trocas — e-mail",'CRM Indústrias'!$B$1:$XFD$1,0),FALSE)=0,"",VLOOKUP($C$15,'CRM Indústrias'!$B:$XFD,MATCH("Trocas — e-mail",'CRM Indústrias'!$B$1:$XFD$1,0),FALSE)),"") | H26: =IFERROR(IF(VLOOKUP($C$15,'CRM Indústrias'!$B:$XFD,MATCH("Trocas — telefone",'CRM Indústrias'!$B$1:$XFD$1,0),FALSE)=0,"",VLOOKUP($C$15,'CRM Indústrias'!$B:$XFD,MATCH("Trocas — telefone",'CRM Indústrias'!$B$1:$XFD$1,0),FALSE)),"")
B27: NFD | C27: =IFERROR(IF(VLOOKUP($C$15,'CRM Indústrias'!$B:$XFD,MATCH("NFD — contato",'CRM Indústrias'!$B$1:$XFD$1,0),FALSE)=0,"",VLOOKUP($C$15,'CRM Indústrias'!$B:$XFD,MATCH("NFD — contato",'CRM Indústrias'!$B$1:$XFD$1,0),FALSE)),"") | E27: =IFERROR(IF(VLOOKUP($C$15,'CRM Indústrias'!$B:$XFD,MATCH("NFD — e-mail",'CRM Indústrias'!$B$1:$XFD$1,0),FALSE)=0,"",VLOOKUP($C$15,'CRM Indústrias'!$B:$XFD,MATCH("NFD — e-mail",'CRM Indústrias'!$B$1:$XFD$1,0),FALSE)),"") | H27: =IFERROR(IF(VLOOKUP($C$15,'CRM Indústrias'!$B:$XFD,MATCH("NFD — telefone",'CRM Indústrias'!$B$1:$XFD$1,0),FALSE)=0,"",VLOOKUP($C$15,'CRM Indústrias'!$B:$XFD,MATCH("NFD — telefone",'CRM Indústrias'!$B$1:$XFD$1,0),FALSE)),"")
B28: Encarte | C28: =IFERROR(IF(VLOOKUP($C$15,'CRM Indústrias'!$B:$XFD,MATCH("Encarte — contato",'CRM Indústrias'!$B$1:$XFD$1,0),FALSE)=0,"",VLOOKUP($C$15,'CRM Indústrias'!$B:$XFD,MATCH("Encarte — contato",'CRM Indústrias'!$B$1:$XFD$1,0),FALSE)),"") | E28: =IFERROR(IF(VLOOKUP($C$15,'CRM Indústrias'!$B:$XFD,MATCH("Encarte — e-mail",'CRM Indústrias'!$B$1:$XFD$1,0),FALSE)=0,"",VLOOKUP($C$15,'CRM Indústrias'!$B:$XFD,MATCH("Encarte — e-mail",'CRM Indústrias'!$B$1:$XFD$1,0),FALSE)),"") | H28: =IFERROR(IF(VLOOKUP($C$15,'CRM Indústrias'!$B:$XFD,MATCH("Encarte — telefone",'CRM Indústrias'!$B$1:$XFD$1,0),FALSE)=0,"",VLOOKUP($C$15,'CRM Indústrias'!$B:$XFD,MATCH("Encarte — telefone",'CRM Indústrias'!$B$1:$XFD$1,0),FALSE)),"")
B29: Lead time / Obs | C29: =IFERROR(IF(VLOOKUP($C$15,'CRM Indústrias'!$B:$XFD,MATCH("Lead time entrega (dias)",'CRM Indústrias'!$B$1:$XFD$1,0),FALSE)=0,"",VLOOKUP($C$15,'CRM Indústrias'!$B:$XFD,MATCH("Lead time entrega (dias)",'CRM Indústrias'!$B$1:$XFD$1,0),FALSE)),"") | E29: =IFERROR(IF(VLOOKUP($C$15,'CRM Indústrias'!$B:$XFD,MATCH("Observações",'CRM Indústrias'!$B$1:$XFD$1,0),FALSE)=0,"",VLOOKUP($C$15,'CRM Indústrias'!$B:$XFD,MATCH("Observações",'CRM Indústrias'!$B$1:$XFD$1,0),FALSE)),"")
B31: ◆ BUSCAR LOGÍSTICA DE CLIENTE
B33: Cliente: | I33: =HYPERLINK("#'Capa - Dashboard'!C33","🗑 Limpar (clique e tecle Delete)") -> 🗑 Limpar (clique e tecle Delete)
B35: Grupo/Rede: | C35: =IFERROR(IF(VLOOKUP($C$33,'Base de Clientes'!$B:$XFD,MATCH("Grupo/Rede",'Base de Clientes'!$B$1:$XFD$1,0),FALSE)=0,"",VLOOKUP($C$33,'Base de Clientes'!$B:$XFD,MATCH("Grupo/Rede",'Base de Clientes'!$B$1:$XFD$1,0),FALSE)),"")
B36: Canal: | C36: =IFERROR(IF(VLOOKUP($C$33,'Base de Clientes'!$B:$XFD,MATCH("Canal",'Base de Clientes'!$B$1:$XFD$1,0),FALSE)=0,"",VLOOKUP($C$33,'Base de Clientes'!$B:$XFD,MATCH("Canal",'Base de Clientes'!$B$1:$XFD$1,0),FALSE)),"")
B37: Cidade: | C37: =IFERROR(IF(VLOOKUP($C$33,'Base de Clientes'!$B:$XFD,MATCH("Cidade",'Base de Clientes'!$B$1:$XFD$1,0),FALSE)=0,"",VLOOKUP($C$33,'Base de Clientes'!$B:$XFD,MATCH("Cidade",'Base de Clientes'!$B$1:$XFD$1,0),FALSE)),"")
B38: UF: | C38: =IFERROR(IF(VLOOKUP($C$33,'Base de Clientes'!$B:$XFD,MATCH("UF",'Base de Clientes'!$B$1:$XFD$1,0),FALSE)=0,"",VLOOKUP($C$33,'Base de Clientes'!$B:$XFD,MATCH("UF",'Base de Clientes'!$B$1:$XFD$1,0),FALSE)),"")
B39: Telefone ERP: | C39: =IFERROR(IF(VLOOKUP($C$33,'Base de Clientes'!$B:$XFD,MATCH("Telefone",'Base de Clientes'!$B$1:$XFD$1,0),FALSE)=0,"",VLOOKUP($C$33,'Base de Clientes'!$B:$XFD,MATCH("Telefone",'Base de Clientes'!$B$1:$XFD$1,0),FALSE)),"")
B40: Agendamento: | C40: =IFERROR(IF(VLOOKUP($C$33,'Base de Clientes'!$B:$XFD,MATCH("Agendado entrega?",'Base de Clientes'!$B$1:$XFD$1,0),FALSE)=0,"",VLOOKUP($C$33,'Base de Clientes'!$B:$XFD,MATCH("Agendado entrega?",'Base de Clientes'!$B$1:$XFD$1,0),FALSE)),"")
B41: Contato agend: | C41: =IFERROR(IF(VLOOKUP($C$33,'Base de Clientes'!$B:$XFD,MATCH("Contato agendamento",'Base de Clientes'!$B$1:$XFD$1,0),FALSE)=0,"",VLOOKUP($C$33,'Base de Clientes'!$B:$XFD,MATCH("Contato agendamento",'Base de Clientes'!$B$1:$XFD$1,0),FALSE)),"")
B42: E-mail agend: | C42: =IFERROR(IF(VLOOKUP($C$33,'Base de Clientes'!$B:$XFD,MATCH("E-mail agendamento",'Base de Clientes'!$B$1:$XFD$1,0),FALSE)=0,"",VLOOKUP($C$33,'Base de Clientes'!$B:$XFD,MATCH("E-mail agendamento",'Base de Clientes'!$B$1:$XFD$1,0),FALSE)),"")
B43: Tel. agend: | C43: =IFERROR(IF(VLOOKUP($C$33,'Base de Clientes'!$B:$XFD,MATCH("Tel. agendamento",'Base de Clientes'!$B$1:$XFD$1,0),FALSE)=0,"",VLOOKUP($C$33,'Base de Clientes'!$B:$XFD,MATCH("Tel. agendamento",'Base de Clientes'!$B$1:$XFD$1,0),FALSE)),"")
B44: Tel. logística: | C44: =IFERROR(IF(VLOOKUP($C$33,'Base de Clientes'!$B:$XFD,MATCH("Tel. logística",'Base de Clientes'!$B$1:$XFD$1,0),FALSE)=0,"",VLOOKUP($C$33,'Base de Clientes'!$B:$XFD,MATCH("Tel. logística",'Base de Clientes'!$B$1:$XFD$1,0),FALSE)),"")
B45: Resp. logística: | C45: =IFERROR(IF(VLOOKUP($C$33,'Base de Clientes'!$B:$XFD,MATCH("Resp. logística",'Base de Clientes'!$B$1:$XFD$1,0),FALSE)=0,"",VLOOKUP($C$33,'Base de Clientes'!$B:$XFD,MATCH("Resp. logística",'Base de Clientes'!$B$1:$XFD$1,0),FALSE)),"")
B46: Obs logística: | C46: =IFERROR(IF(VLOOKUP($C$33,'Base de Clientes'!$B:$XFD,MATCH("Obs logística",'Base de Clientes'!$B$1:$XFD$1,0),FALSE)=0,"",VLOOKUP($C$33,'Base de Clientes'!$B:$XFD,MATCH("Obs logística",'Base de Clientes'!$B$1:$XFD$1,0),FALSE)),"")
B49: =HYPERLINK("file:///Users/marcelorodrigues/Library/CloudStorage/GoogleDrive-marcelo%403mvrepresentacao.com/Meu%20Drive/3MV/CRM%203MV/_executaveis/Atualizar%20CRM.app","🍎 ATUALIZAR CRM (Mac)") -> 🍎 ATUALIZAR CRM (Mac) | G49: =HYPERLINK("file:///Users/marcelorodrigues/Library/CloudStorage/GoogleDrive-marcelo%403mvrepresentacao.com/Meu%20Drive/3MV/CRM%203MV/_executaveis/Atualizar%20CRM%203MV.bat","🪟 ATUALIZAR CRM (Windows)") -> 🪟 ATUALIZAR CRM (Windows)
B52: ◆ IR PARA
B54: =HYPERLINK("#'CRM Indústrias'!A1","▶ CRM Indústrias") -> ▶ CRM Indústrias | E54: =HYPERLINK("#'Base de Clientes'!A1","▶ Base de Clientes") -> ▶ Base de Clientes | H54: =HYPERLINK("#'Evolução Anual'!A1","▶ Evolução Anual") -> ▶ Evolução Anual
B57: Botões 🍎 (Mac) e 🪟 (Windows) puxam dados novos da API Suas Vendas. Tudo que você preencheu nas colunas amarelas é preservado entre atualizações.

Sheet CRM Indústrias
A1: ID | B1: Indústria | C1: Razão Social | D1: CNPJ | E1: Status ERP | F1: Financeiro — contato | G1: Financeiro — e-mail | H1: Financeiro — telefone | I1: Contas a Pagar — contato | J1: Contas a Pagar — e-mail | K1: Contas a Pagar — telefone | L1: Contas a Receber — contato | M1: Contas a Receber — e-mail | N1: Contas a Receber — telefone | O1: Marketing — contato | P1: Marketing — e-mail | Q1: Marketing — telefone | R1: ADM — contato | S1: ADM — e-mail | T1: ADM — telefone | U1: Gerência — contato | V1: Gerência — e-mail | W1: Gerência — telefone | X1: Supervisão — contato | Y1: Supervisão — e-mail | Z1: Supervisão — telefone | AA1: Trocas — contato | AB1: Trocas — e-mail | AC1: Trocas — telefone | AD1: NFD — contato | AE1: NFD — e-mail | AF1: NFD — telefone | AG1: Encarte — contato | AH1: Encarte — e-mail | AI1: Encarte — telefone | AJ1: Lead time entrega (dias) | AK1: Observações
A2: 893 | B2: BR Spice | C2: BR SPICES INDUSTRIA E COMERCIO DE ALIMENTOS S.A. | D2: 21.418.616/0001-57 | E2: Ativo | F2: Yasmin | G2: yasmin.cerqueira@brspices.com.br | H2: (11) 99282-2460 | L2: Celia | N2: (11) 93908-3486 | R2: Heloísa | S2: admvendas@brspices.com.br | T2: (11) 98918-0943 | U2: Icaro | V2: icaro.pereira@brspices.com.br | W2: (31) 99069-3741
A3: 881 | B3: Casa Madeia | C3: ADEGA CASA DE MADEIRA LTDA | D3: 94.904.133/0001-36 | E3: Ativo | F3: Gesiane | G3: gesiane.morais@famigliavalduga.com.br | H3: (54) 2105-3122 | L3: Cristiane | M3: cristiane.pereira@famigliavalduga.com.br | N3: (54) 99222-4642 | R3: Elisandra | S3: elisandra.aimi@famigliavalduga.com.br | T3: (54) 98128-5310 | U3: Angela | V3: angela.guedes@famigliavalduga.com.br | W3: (54) 98128-5310
A4: 70 | B4: Condor | C4: CONDOR S/A | D4: 86.046.448/0001-61 | E4: Ativo | F4: Oriane | G4: oriane.souza@condor.ind.br | H4: (47) 3631-2420 | R4: Jennifer | S4: jennifer.weber@condor.ind.br | T4: 0800 047 6767 | U4: Rubens Spada | V4: rubens.spada@condor.ind.br | W4: (11) 97016-0425 | AA4: Claudineia | AB4: claudineia.oracz@condor.ind.br | AC4: (47) 99722-1421 | AD4: Claudineia | AE4: claudineia.oracz@condor.ind.br | AF4: (47) 99722-1421
A5: 62 | B5: Dana | C5: PERFUMES DANA DO BRASIL S.A. | D5: 61.105.722/0005-29 | E5: Ativo | F5: Financeiro | G5: contasareceber@danacosmeticos.com.br | H5: (11) 3065-1569; (11) 2842-3245 | I5: Carlos Andre | J5: contasapagar@danacosmeticos.com.br | K5: (11) 2842-3262 | L5: Financeiro | M5: contasareceber@danacosmeticos.com.br | N5: (11) 3065-1569; (11) 2842-3245 | O5: Tiago Espires | P5: tiago.espires@danacosmeticos.com.br | Q5: (11) 99560-0499 | R5: Lais | S5: lais.araujo@danacosmeticos.com.br | T5: (11) 94250-2993 | U5: Rosana (Farma) ; Airton ( Atacado) ; Leonardo (Varejo) | V5: rosana.pereira@danacosmeticos.com.br ; airton.barboza@danacosmeticos.com.br; leonardo.Mesquita@danacosmeticos.com.br | W5: (11) 99559-5338 ; (11) 98188-0172; (31) 99678-4719 | AA5: Bruno Zieri | AB5: bruno.zieri@danacosmeticos.com.br | AC5: (11) 94250-3042 | AD5: Bruno Zieri | AE5: bruno.zieri@danacosmeticos.com.br | AF5: (11) 94250-3042 | AG5: Thiago | AH5: thiago.souza@danacosmeticos.com.br | AI5: (31) 98266-4293
A6: 886 | B6: Domno | C6: DOMNO DO BRASIL INDUSTRIA E COMERCIO DE BEBIDAS LTDA | D6: 09.276.690/0001-80 | E6: Ativo | F6: Gesiane | G6: gesiane.morais@famigliavalduga.com.br | H6: (54) 2105-3122 | L6: Cristiane | M6: cristiane.pereira@famigliavalduga.com.br | N6: (54) 99222-4642 | R6: Elisandra | S6: elisandra.aimi@famigliavalduga.com.br | T6: (54) 98128-5310 | U6: Angela | V6: angela.guedes@famigliavalduga.com.br | W6: (54) 98128-5310
A7: 889 | B7: JACQUES JANINE | C7: BR COSMETIC COMERCIAL LTDA | D7: 17.079.462/0001-49 | E7: Ativo | F7: Elisabete | G7: financeiro2@brcosmetic.com | H7: (11) 97454-1983 | L7: Elisabete | M7: financeiro2@brcosmetic.com | N7: (11) 97454-1983 | O7: Isabella Frediani | P7: design.mkt@brcosmetic.com | Q7: (11) 91594-8226 | R7: Morgana | S7: comercial1@brcosmetic.com | T7: (11) 99835-2076 | X7: Mario | Z7: (11) 97227-2772 | AA7: Gabriel | AB7: devolucao@brcosmetic.com | AC7: (11) 94110-6734 | AD7: Gabriel | AE7: devolucao@brcosmetic.com | AF7: (11) 94110-6734 | AG7: Isabella Frediani | AH7: design.mkt@brcosmetic.com | AI7: (11) 91594-8226
A8: 887 | B8: Kanitz | C8: CDA - DISTRIBUIDORA DE COSMETICOS LTDA. | D8: 06.128.346/0001-56 | E8: Ativo | F8: Edilson | G8: financas@dicoserj.com.br | L8: Edilson | M8: financas@dicoserj.com.br | O8: Lucinea | P8: marketing1@kanitz1900.com.br; marketing2@kanitz1900.com.br | R8: Marcelo | S8: marcelo@kanitz1900.com.br | T8: (21) 98212-7882 | U8: Anderson | V8: anderson@kanitz1900br.onmicrosoft.com | W8: (21) 97232-8314 | AA8: Marcelo | AB8: marcelo@kanitz1900.com.br | AC8: (21) 98212-7882 | AD8: Marcelo | AE8: marcelo@kanitz1900.com.br | AF8: (21) 98212-7882 | AG8: Lucinea | AH8: marketing1@kanitz1900.com.br; marketing2@kanitz1900.com.br
A9: 880 | B9: Leopoldina | C9: CERVEJARIA LEOPOLDINA LTDA | D9: 22.226.696/0001-01 | E9: Ativo | F9: Gesiane | G9: gesiane.morais@famigliavalduga.com.br | H9: (54) 2105-3122 | L9: Cristiane | M9: cristiane.pereira@famigliavalduga.com.br | N9: (54) 99222-4642 | R9: Elisandra | S9: elisandra.aimi@famigliavalduga.com.br | T9: (54) 98128-5310 | U9: Angela | V9: angela.guedes@famigliavalduga.com.br | W9: (54) 98128-5310
A10: 66 | B10: M Dias | C10: M DIAS BRANCO S.A. INDUSTRIA E COMERCIO DE ALIMENTOS | D10: 07.206.816/0042-93 | E10: Ativo
A11: 656 | B11: Melbras | C11: MELBRAS IMPORTADORA E EXPORTADORA AGROINDUSTRIA LTDA | D11: 11.871.823/0001-09 | E11: Ativo | F11: Gisele | G11: financeiro@melbras.com.br | H11: (31) 99622-7104 | L11: Gisele | M11: financeiro@melbras.com.br | N11: (31) 99622-7104 | R11: Leticia | S11: comercial3@melbras.com.br | T11: (31) 9704-3785 | U11: Pablo | V11: pablo.marcio@melbras.com.br | W11: (31) 9987-4726
A12: 709 | B12: Ruby Rose | C12: UNION MEDIC COMERCIO E REPRESENTACAO DE PRODUTOS PARA A SAUDE LTDA | D12: 45.143.429/0001-76 | E12: Ativo
A13: 63 | B13: Semina | C13: SEMINA IND COM LT | D13: 55.163.042/0001-35 | E13: Ativo
A14: 60 | B14: Tia Sonia | C14: ALIMENTOS TIA SONIA LTDA | D14: 08.385.685/0002-24 | E14: Ativo
A15: 869 | B15: Upper | C15: UPPER DOG COMERCIAL LTDA | D15: 22.468.303/0005-08 | E15: Ativo
A16: 882 | B16: Valduga | C16: CASA VALDUGA VINHOS FINOS LTDA | D16: 87.848.180/0001-44 | E16: Ativo | F16: Gesiane | G16: gesiane.morais@famigliavalduga.com.br | H16: (54) 2105-3122 | L16: Cristiane | M16: cristiane.pereira@famigliavalduga.com.br | N16: (54) 99222-4642 | R16: Elisandra | S16: elisandra.aimi@famigliavalduga.com.br | T16: (54) 98128-5310 | U16: Angela | V16: angela.guedes@famigliavalduga.com.br | W16: (54) 98128-5310

Sheet Base de Clientes
A1: ID | B1: Nome fantasia | C1: Grupo/Rede | D1: Canal | E1: Razão social | F1: CNPJ | G1: Cidade | H1: UF | I1: Telefone | J1: E-mail | K1: Pessoa | L1: Status | M1: Comprou 2023-26? | N1: Agendado entrega? | O1: Contato agendamento | P1: E-mail agendamento | Q1: Tel. agendamento | R1: Tel. logística | S1: Resp. logística | T1: Obs logística
A2: 612 | B2: .com açai | C2: — | D2: Açaí | E2: KEILA ALVES RAMALHO 12474483632 | F2: 37.745.450/0001-13 | G2: Governador Valadares | H2: MG | I2: (33) 99148-1635 | J2: keillinha_gv10@hotmail.com | K2: PJ | L2: Inativo | M2: —
A3: 449 | B3: 3MV REPRESENTACOES | C3: — | D3: Representações | E3: 3MV REPRESENTACOES LTDA - ME | F3: 26.424.501/0001-99 | G3: IPATINGA | H3: MG | I3: 31 3822 4687 | J3: marcelo@3mvrepresentacao.com | K3: PJ | L3: Ativo | M3: Sim
A4: 716 | B4: A GRANEL | C4: — | D4: Açaí | E4: LIGEIRO & PIRES PRODUTOS NATURAIS LTDA | F4: 26.822.115/0001-55 | H4: MG | I4: (33) 3322-4000 | J4: MEMCONTABILIDADE@GMAIL.COM | K4: PJ | L4: Inativo | M4: —
A5: 431 | B5: ACAI & CIA | C5: — | D5: Açaí | E5: MGE ACAI E CIA LTDA | F5: 23.913.733/0001-12 | G5: GOVERNADOR VALADARES | H5: MG | I5: (33) 3021-1652 | J5: gustavovazvillela@hotmail.com | K5: PJ | L5: Ativo | M5: Sim
A6: 563 | B6: ACAI CAFE | C6: — | D6: Açaí | E6: DEBORA DE JESUS OLIVEIRA 14037816644 | F6: 36.769.580/0001-23 | G6: Coronel Fabriciano | H6: MG | I6: (31) 98585-6120 | J6: richardson19@globo.com | K6: PJ | L6: Inativo | M6: —
A7: 485 | B7: ACAI CULTURA | C7: — | D7: Açaí | E7: MARIA COSTA SOARES FERRREIRA DE LIMA 30733090630 | F7: 29.865.404/0001-20 | G7: Ipatinga | H7: MG | I7: (31) 3822-3117 | J7: acaicultura@gmail.com | K7: PJ | L7: Inativo | M7: —
A8: 523 | B8: ACAI CULTURA | C8: — | D8: Açaí | E8: ACAICULTURA ALIMENTOS LTDA | F8: 33.269.510/0001-18 | G8: Ipatinga | H8: MG | I8: 31 99400 9797 | J8: thiago.acaicultura@gmail.com | K8: PJ | L8: Inativo | M8: —
A9: 688 | B9: ACAI DICASA | C9: — | D9: Açaí | E9: FABIANO GONCALVES LIBOREIRO 06926987602 | F9: 38.043.185/0001-94 | G9: Governador Valadares | H9: MG | I9: (31) 9546-1035 | J9: FABIANO.LIBOREIRO@YAHOO.COM | K9: PJ | L9: Inativo | M9: —
A10: 507 | B10: ACAI DO ARITANA | C10: — | D10: Açaí | E10: JOAO PAULO SILVA SALES 0218795606 | F10: 32.539.031/0001-01 | G10: Governador Vala | H10: MG | I10: 33 98712 7985 | J10: joao191ja@gmail.com | K10: PJ | L10: Inativo | M10: —
A11: 508 | B11: ACAI DO SIRLEI | C11: — | D11: Açaí | E11: VITORIA FERNANDES SILVA 13021856675 | F11: 33.310.998/0001-80 | G11: Governador Vala | H11: MG | I11: 33 99971 5891 | J11: mais_atacadista@hotmail.com | K11: PJ | L11: Ativo | M11: —
A12: 561 | B12: ACAI DOS VALES | C12: — | D12: Açaí | E12: NILDA SANTOS PEREIRA 09963832636 | F12: 33.956.901/0001-00 | G12: Governador Vala | H12: MG | I12: 33 98727 2889 | J12: arturcastor@hotmail.com | K12: PJ | L12: Ativo | M12: —
A13: 747 | B13: ACAI FRUIT SHOW COLATINA | C13: — | D13: — | E13: ACAI FRUIT SHOW COLATINA LTDA | F13: 44.216.367/0001-12 | G13: COLATINA | H13: ES | I13: (31) 9122-4771 | J13: ANTONIELEBARBOSA1@GMAIL.COM | K13: PJ | L13: Inativo | M13: Sim
A14: 533 | B14: ACAI FRUIT SHOW GV | C14: — | D14: Açaí | E14: ACAI FRUIT SHOW GV LTDA | F14: 31.140.821/0001-57 | G14: GOVERNADOR VALA | H14: MG | I14: 31 9122 4771 | J14: antonielebarbosa1@gmail.com | K14: PJ | L14: Inativo | M14: Sim
A15: 652 | B15: ACAI FRUIT SHOW IPATINGA | C15: — | D15: Açaí | E15: ACAI FRUIT SHOW IPATINGA LTDA | F15: 42.963.776/0001-57 | G15: IPATINGA | H15: MG | I15: (31) 9389-0076 | J15: NANTESGAS@HOTMAIL.COM | K15: PJ | L15: Inativo | M15: Sim
A16: 514 | B16: ACAI FRUIT SHOW TEOFILO OTONI | C16: — | D16: Açaí | E16: ACAI FRUIT SHOW TEOFILO OTONI EIRELI | F16: 28.791.305/0001-88 | G16: TEOFILO OTONI | H16: MG | I16: 31 99122 4771 | J16: acaishow@hotmail.com | K16: PJ | L16: Inativo | M16: Sim
... A29: 530 | B29: AMARETTO IPATINGA | C29: — | D29: Açaí | E29: M E M FILHOS SORVETERIA E CAFETERIA EIRELI | F29: 31.688.061/0001-17 | G29: Ipatinga | H29: MG | I29: 31 98869 8830 | J29: mhmiranda@uol.com.br | K29: PJ | L29: Ativo | M29: —
A30: 705 | B30: AMORIM SUPERMERCADO | C30: — | D30: Supermercado | E30: JTB AMORIM SUPERMERCADOS EIRELI | F30: 03.476.613/0001-98 | H30: MG | I30: (33) 3533-1326 | J30: AMORIMSUPERMERCADO@HOTMAIL.COM.BR | K30: PJ | L30: Inativo | M30: —
A31: 535 | B31: ANDRADE DISTRIBUIDOR | C31: Andrade Distribuidora | D31: Atacarejo | E31: PADARIA E DISTRIBUIDORA CARAVELAS LTDA | F31: 08.056.022/0002-66 | G31: IPATINGA | H31: MG | I31: 31 3825 7407 | J31: distribuidora.andrade@hotmail.com | K31: PJ | L31: Inativo | M31: —
A32: 662 | B32: ANDRADE DISTRIBUIDORA | C32: Andrade Distribuidora | D32: Distribuidor | E32: PADARIA E DISTRIBUIDORA CARAVELAS LTDA | F32: 08.056.022/0001-85 | G32: IPATINGA | H32: MG | I32: (31) 3822-6480 | J32: RRMCONT@UOL.COM.BR | K32: PJ | L32: Inativo | M32: Sim
A33: 517 | B33: ARAUJO E AMORIM | C33: — | D33: Açaí | E33: ARAUJO E AMORIM LTDA | F33: 23.625.927/0001-12 | G33: CARATINGA | H33: MG | I33: 33 99996 6906 | J33: thatianeinaria@hotmail.com | K33: PJ | L33: Inativo | M33: Sim
A34: 358 | B34: ARMAZEM A GRANEL | C34: — | D34: Açaí | E34: HUMBERTO LUCAS BATISTA COSTA 01668515660 | F34: 33.322.542/0001-30 | G34: TIMOTEO | H34: MG | I34: 31 2136 7475 | J34: armazemgranel2020@gmail.com | K34: PJ | L34: Inativo | M34: —
A35: 460 | B35: ARMAZEM DO ACAI | C35: — | D35: Açaí | E35: K V SANTUZZI LANCHONETE | F35: 29.558.496/0001-03 | G35: GOVERNADOR VALA | H35: MG | I35: 33 98749 1638 | J35: armazemdoacaigv@hotmail.com | K35: PJ | L35: Ativo | M35: Sim
A36: 586 | B36: ARMAZEM FIT STORE | C36: — | D36: Açaí | E36: NUTRIR COMERCIO DE ALIMENTOS EIRELI | F36: 33.002.358/0001-02 | G36: IPATINGA | H36: MG | I36: 31 98603 1071 | K36: PJ | L36: Inativo | M36: —
A37: 551 | B37: ARMAZEM SAUDE EM GRA | C37: — | D37: Açaí | E37: CLAUDIA DO CARMO ASSIS 04507372682 | F37: 35.094.535/0001-53 | G37: IPATINGA | H37: MG | I37: 31 99396 9906 | J37: claudiaassis@yahoo.com.br | K37: PJ | L37: Prospectado | M37: —
A38: 416 | B38: ARTE LOCACOES | C38: — | D38: Atacado | E38: ARTE LOCACOES E PROMOCOES LTDA ME | F38: 26.261.453/0001-65 | G38: GOVERNADOR VALA | H38: MG | I38: 31 3424 8000 | J38: majellacosta@gmail.com | K38: PJ | L38: Prospectado | M38: —
A39: 465 | B39: ATACADO SANTA MARIA | C39: — | D39: Atacarejo | E39: ATACADAO SANTA MARIA LTDA | F39: 20.446.391/0001-80 | G39: SANTA MARIA DE | H39: MG | I39: 31 3838 1212 | J39: nfe.atacadaosmi@gmail.com | K39: PJ | L39: Inativo | M39: Sim
A40: 360 | B40: ATACADÃO S. FURTADO 02 | C40: S. Furtado | D40: Atacado | E40: S FURTADO DA SILVA E CIA LTDA | F40: 41.793.050/0003-12 | G40: IPANEMA | H40: MG | I40: 33 3314 1566 | J40: compras@atacadaosfurtado.com.br <compras@atacadaosfurtado.com.br>; | K40: PJ | L40: Ativo | M40: Sim
A41: 432 | B41: ATACAFORTE | C41: Atacaforte | D41: Atacarejo | E41: IRMAOS SOARES LTDA | F41: 20.604.518/0001-41 | G41: GOVERNADOR VALA | H41: MG | I41: 33 3213 5400 | J41: xmlvilaisa@atacaforte.com.br;xml@atacaforte.com.br | K41: PJ | L41: Inativo | M41: —
A42: 434 | B42: ATACAFORTE LJ 02 | C42: Atacaforte | D42: Atacarejo | E42: IRMAOS SOARES LTDA | F42: 20.604.518/0006-56 | G42: GOVERNADOR VALA | H42: MG | I42: 33 3213 5400 | J42: xml@atacaforte.com.br;xmlvilaisa@atacaforte.com.br | K42: PJ | L42: Inativo | M42: —
A43: 435 | B43: ATACAFORTE LJ 03 | C43: Atacaforte | D43: Atacarejo | E43: IRMAOS SOARES LTDA | F43: 20.604.518/0007-37 | G43: GOVERNADOR VALA | H43: MG | I43: 33 3275 1111 | J43: xmlvilaisa@atacaforte.com.br | K43: PJ | L43: Inativo | M43: —
A44: 433 | B44: ATACAFORTE LJ 1 | C44: Atacaforte | D44: Atacarejo | E44: IRMAOS SOARES LTDA | F44: 20.604.518/0002-22 | G44: GOVERNADOR VALA | H44: MG | I44: 33 3213 5400 | J44: xml@atacaforte.com.br | K44: PJ | L44: Inativo | M44: —
A45: 867 | B45: ATACAREJO SAO JOAO - ABRE CAMPO | C45: São João / Gardingo | D45: — | E45: DISTRIBUIDORA IRMAOS GARDINGO IND. COMERCIO E TRANSPORTES LTDA | F45: 18.861.682/0012-45 | G45: Abre Campo | H45: MG | I45: (31) 8421-3403 | J45: CONTABILIDADE@GARDINGO.COM.BR | K45: PJ | L45: Ativo | M45: Sim
A46: 504 | B46: ATACAREJO SÃO JOAO | C46: São João / Gardingo | D46: Atacarejo | E46: DISTRIBUIDORA IRMAOS GARDINGO IND COMERCIO E TRANSPORTES LTDA | F46: 18.861.682/0009-40 | G46: MATIPO | H46: MG | I46: 31 387 31407 | J46: danfe@superirmao.com.br; nfe@gardingo.com.br;gardingo@gardingo.com.br | K46: PJ | L46: Ativo | M46: Sim
A47: 378 | B47: ATENAS | C47: — | D47: Distribuidor | E47: ATENAS DISTRIBUICAO INTELIGENTE LTDA | F47: 31.130.627/0001-90 | G47: CONTAGEM | H47: MG | I47: 31 98805 6364 | J47: logistica@atenasdistribuicao.com.br;jovem@atenasdistribuicao.com.br | K47: PJ | L47: Inativo | M47: —
A48: 685 | B48: BAMBINO | C48: — | D48: — | E48: BAMBINO PRESENTES LTDA | F48: 04.458.732/0001-80 | G48: Manhuaçu | H48: MG | I48: (33) 3331-1033 | J48: BFRANK@SOFT-HARD.COM.BR | K48: PJ | L48: Inativo | M48: —
A49: 885 | B49: BARAO COSMETICOS | C49: — | D49: — | E49: BOTELHO & DAMAZIO COSMETICOS LTDA | F49: 47.350.738/0001-42 | G49: Barão de Cocais | H49: MG | I49: (31) 9872-3923 | K49: PJ | L49: Inativo | M49: —
A50: 840 | B50: BEAUTY CENTER | C50: — | D50: — | E50: ISRAEL SANTOS ROCHA 08371370636 | F50: 45.421.814/0001-38 | G50: Nanuque | H50: MG | I50: (33) 3621-4132 | J50: PONTUALCONTABILIDADEMG@GMAIL.COM | K50: PJ | L50: Inativo | M50: Sim
A51: 638 | B51: BELEZA & CIA | C51: — | D51: Perfumaria | E51: OSEAS OLIVEIRA SILVA & CIA LTDA | F51: 02.698.472/0001-95 | G51: Governador Valadares | H51: MG | K51: PJ | L51: Inativo | M51: Sim
A52: 680 | B52: BELLA CASA | C52: — | D52: Utilidade | E52: E. S. SANTOS UTILIDADES DOMESTICAS | F52: 35.973.397/0001-82 | G52: CARATINGA | H52: MG | I52: (33) 3321-3931 | J52: MARCAGESTAOCONTABIL@GMAIL.COM | K52: PJ | L52: Inativo | M52: —
A53: 728 | B53: Bella Mix Cosméticos | C53: — | D53: — | E53: VANIA MARIA FERREIRA COELHO | F53: 40.830.151/0001-91 | G53: GOVERNADOR VALADARES | H53: MG | I53: (33) 9911-91704 | J53: bellamixgv@hotmail.com | K53: PJ | L53: Inativo | M53: —
A54: 765 | B54: BELLACENTER DISTRIBUIDORA | C54: — | D54: Distribuidor | E54: DIBH - DISTRIBUIDORA BELEZA HIGIENE LTDA | F54: 18.535.681/0001-58 | G54: Uberaba | H54: MG | I54: (34) 9917-8815 | J54: HERNANI@BELLACENTERDISTRIBUIDORA.COM.BR | K54: PJ | L54: Inativo | M54: Sim
A55: 365 | B55: BENDITO AÇAI GV | C55: — | D55: Açaí | E55: TATIANE DORNELAS DE SOUZA | F55: 40.297.346/0001-18 | G55: Governador Valadares | H55: MG | I55: 33 99126 8238 | K55: PJ | L55: Ativo | M55: —
A56: 454 | B56: BIG MAIS SUPERMERCAD | C56: Big Mais | D56: Supermercado | E56: BIG MAIS SUPERMERCADOS LTDA | F56: 07.263.762/0007-15 | G56: Governador Vala | H56: MG | I56: 33 3275 6192 | J56: natasha@bigmais.com.br; fiscal@bigmais.com.br | K56: PJ | L56: Ativo | M56: Sim
A57: 598 | B57: BIG MAIS SUPERMERCADO ALTINOPOLIS | C57: Big Mais | D57: Supermercado | E57: BIG MAIS SUPERMERCADOS LTDA | F57: 07.263.762/0005-53 | G57: GOVERNADOR VALA | H57: MG | I57: 33 3278 7200 | J57: fiscal@bigmais.com.br ; natasha@bigmais.com.br | K57: PJ | L57: Inativo | M57: —
A58: 596 | B58: BIG MAIS SUPERMERCADO JARDIM PEROLA | C58: Big Mais | D58: Supermercado | E58: BIG MAIS SUPERMERCADOS LTDA | F58: 07.263.762/0001-20 | G58: Governador Vala | H58: MG | I58: 33 3273 8800 | J58: fiscal@bigmais.com.br ; natasha@bigmais.com.br | K58: PJ | L58: Inativo | M58: —
A59: 597 | B59: BIG MAIS SUPERMERCADO LAGOA SANTA | C59: Big Mais | D59: Supermercado | E59: BIG MAIS SUPERMERCADOS LTDA | F59: 07.263.762/0004-72 | G59: Governador Vala | H59: MG | I59: 33 3278 0080 | J59: fiscal@bigmais.com.br ; natasha@bigmais.com.br | K59: PJ | L59: Inativo | M59: —
A60: 599 | B60: BIG MAIS SUPERMERCADO SÃO PAULO | C60: Big Mais | D60: Supermercado | E60: BIG MAIS SUPERMERCADOS LTDA | F60: 07.263.762/0003-91 | G60: GOVERNADOR VALA | H60: MG | I60: 33 3212 7550 | J60: fiscal@bigmais.com.br ; natasha@bigmais.com.br | K60: PJ | L60: Inativo | M60: —
A61: 600 | B61: BIG MAIS SUPERMERCADO SÃO PEDRO | C61: Big Mais | D61: Supermercado | E61: BIG MAIS SUPERMERCADOS LTDA | F61: 07.263.762/0009-87 | G61: GOVERNADOR VALA | H61: MG | I61: 33 3275-6192 | J61: fiscal@bigmais.com.br ; natasha@bigmais.com.br | K61: PJ | L61: Inativo | M61: —
A62: 847 | B62: BIG PLUS SUPERMERCADO | C62: — | D62: — | E62: BIG PLUS SUPERMERCADO LTDA | F62: 05.149.076/0001-05 | G62: Timóteo | H62: MG | I62: (31) 3847-4145 | J62: COELHOSUPERMERCADO@HOTMAIL.COM | K62: PJ | L62: Inativo | M62: Sim
A63: 918 | B63: BIOFLORA JANAUBA | C63: — | D63: — | E63: FLAVIA COMERCIO DE VINHOS E PRODUTOS NATURAIS LTDA | F63: 22.095.396/0001-30 | G63: Janaúba | H63: MG | I63: (38) 3821-2692 | J63: LEGALIZA@AUCCONCONTABILIDADE.CNT.BR | K63: PJ | L63: Inativo | M63: Sim
A64: 565 | B64: BISCOITERIA DELICIAS | C64: — | D64: Açaí | E64: BISCOITERIA DELICIAS DA VIDA LTDA | F64: 38.013.250/0001-39 | G64: IPATINGA | H64: MG | I64: 31 98465 3656 | J64: biscoiteria.deliciasdavida@gmail.com | K64: PJ | L64: Prospectado | M64: —
A65: 541 | B65: BRASIL SUPERMERCADOS CIDADE NOBRE | C65: Supermercado Brasil | D65: Supermercado | E65: SUPERMERCADO DEGRAU LTDA | F65: 02.912.729/0005-93 | G65: IPATINGA | H65: MG | I65: 31 3822 0471 | J65: nfecidadenobre@brasilsupermercados.com.br | K65: PJ | L65: Inativo | M65: Sim
A66: 540 | B66: BRASIL SUPERMERCADOS PANORAMA | C66: Supermercado Brasil | D66: Supermercado | E66: SUPERMERCADO DEGRAU LTDA | F66: 02.912.729/0006-74 | G66: IPATINGA | H66: MG | I66: 31 3845 4050 | J66: nfe08@brasilsupermercados.com.br | K66: PJ | L66: Inativo | M66: Sim
A67: 542 | B67: BRASIL SUPERMERCADOS TIMOTEO | C67: Supermercado Brasil | D67: Supermercado | E67: SUPERMERCADO DEGRAU LTDA | F67: 02.912.729/0004-02 | G67: TIMOTEO | H67: MG | I67: 31 3849 6381 | J67: nfedistrito@brasilsupermercados.com.br | K67: PJ | L67: Inativo | M67: Sim
... A72: 468 | B72: CARAMEL ATACADISTA | C72: — | D72: Atacado | E72: CARAMEL ATACADISTA LTDA - ME | F72: 28.501.301/0001-18 | G72: Caratinga | H72: MG | I72: 33 3321 6080 | J72: compras@caramelatacadista.com.br | K72: PJ | L72: Inativo | M72: —
A73: 661 | B73: CARNES & CIA | C73: — | D73: Mercearia | E73: CASA DE CARNES PEREIRA & SILVA LTDA | F73: 86.414.109/0001-90 | G73: Ipatinga | H73: MG | K73: PJ | L73: Inativo | M73: —
A74: 381 | B74: CASA ALADIM BA | C74: — | D74: Distribuidor | E74: DCA DISTRIBUIDORA DE COSMETICOS LTDA | F74: 31.912.909/0001-40 | G74: Feira de Santana | H74: BA | I74: (33) 3529-3301 | J74: financeiro@casaaladim.com.br;compras.2@casaaladim.com.br | K74: PJ | L74: Ativo | M74: Sim
A75: 701 | B75: CASA ALADIM BETIM MG | C75: — | D75: — | E75: DAC DISTRIBUIDORA DE COSMETICOS LTDA | F75: 45.454.137/0001-54 | G75: Betim | H75: MG | I75: (31) 2510-5278 | J75: CONTATO@MUTUUSCONTABILIDADE.COM.BR | K75: PJ | L75: Ativo | M75: Sim
A76: 377 | B76: CASA ALADIM MG | C76: — | D76: Distribuidor | E76: CASA ALADIM LTDA - MG | F76: 25.113.317/0001-65 | G76: TEÓFILO OTONI | H76: MG | I76: 33 99132 8906 | J76: financeiro@casaaladim.com.br;compras.2@casaaladim.com.br | K76: PJ | L76: Inativo | M76: Sim
A77: 429 | B77: CASA DA NATUREZA | C77: — | D77: Açaí | E77: CASA DA NATUREZA LTDA - ME | F77: 05.284.730/0001-85 | G77: GOVERNADOR VALA | H77: MG | I77: 33 3221 0288 | J77: casanatureza@hotmail.com | K77: PJ | L77: Prospectado | M77: —
A78: 550 | B78: CASA DO ACAI | C78: — | D78: Açaí | E78: WAGNER THIAGO FERNANDES DE SOUZA 07335097622 | F78: 14.631.061/0001-61 | G78: Governador Vala | H78: MG | I78: 33 3276 3589 | J78: wagnerthiago10@hotmail.com | K78: PJ | L78: Ativo | M78: —
A79: 756 | B79: CASA DO BISCOITO | C79: — | D79: — | E79: COMERCIO DE DOCES MANHUACU LTDA | F79: 45.485.038/0001-30 | G79: Manhuaçu | H79: MG | I79: (33) 3331-1115 | J79: CONTATO.NIVERSOSIMAO@GMAIL.COM | K79: PJ | L79: Inativo | M79: Sim
A80: 757 | B80: CASA DO BISCOITO DE CARATINGA | C80: — | D80: — | E80: COMERCIO DE DOCES CARATINGA LTDA | F80: 18.828.290/0001-21 | G80: Caratinga | H80: MG | I80: (33) 98443-9181 | J80: CONTATO.NIVERSOSIMAO@GMAIL.COM | K80: PJ | L80: Inativo | M80: Sim
A81: 839 | B81: CASA DO CABELEIREIRO DE CARATINGA | C81: — | D81: — | E81: 18.850.852 GENIDALVA DAVINA DE JESUS VIEIRA | F81: 18.850.852/0001-33 | G81: Caratinga | H81: MG | I81: (33) 3322-2871 | J81: GENIDALVADEJESUSVIEIRA@GMAIL.COM | K81: PJ | L81: Inativo | M81: Sim
A82: 635 | B82: CASA DO CABELEREIRO | C82: — | D82: Perfumaria | E82: COMERCIAL AMARAL EIRELI | F82: 29.358.640/0001-50 | G82: Ipatinga | H82: MG | I82: (31) 3822-4687 | J82: DESCONCONTABILIDADE@HOTMAIL.COM | K82: PJ | L82: Inativo | M82: —
A83: 679 | B83: CASA DOS COSMETICOS | C83: — | D83: Perfumaria | E83: FEIRAO DOS COSMETICOS LTDA | F83: 66.281.825/0001-30 | G83: GOVERNADOR VALADARES | H83: MG | I83: (33) 3021-2121 | J83: WALTONSCONTABILIDADE@HOTMAIL.COM | K83: PJ | L83: Inativo | M83: —
A84: 784 | B84: CASA PINHO | C84: — | D84: — | E84: CASA PINHO LTDA | F84: 18.674.960/0001-00 | G84: Sabinópolis | H84: MG | K84: PJ | L84: Inativo | M84: Sim
A85: 458 | B85: CASTANHAS DO VALE | C85: — | D85: Açaí | E85: MARCELO REZENDE QUEIROZ 81341423620 | F85: 32.061.347/0001-30 | G85: IPATINGA | H85: MG | I85: 33 3825 3383 | J85: CASTANHASDOVALE@GMAIL.COM | K85: PJ | L85: Inativo | M85: —
A86: 873 | B86: CD GARCIA JARDIM PANORAMA | C86: Garcia Supermercados | D86: — | E86: SUPERACO ALIMENTOS LTDA | F86: 08.335.717/0009-53 | G86: Ipatinga | H86: MG | I86: (31) 3829-7350 | J86: CONTABIL@GARCIASUPERMERCADOS.COM.BR | K86: PJ | L86: Inativo | M86: Sim
A87: 759 | B87: CENTRAL SUPERMERCADOS | C87: — | D87: Supermercado | E87: CENTRAL SUPERMERCADOS EIRELI | F87: 08.019.075/0001-26 | G87: Conselheiro Pena | H87: MG | K87: PJ | L87: Inativo | M87: Sim
A88: 669 | B88: CEVAROLI FILIAL | C88: Cevaroli / OPA | D88: Supermercado | E88: CEVAROLI SUPERMERCADOS LTDA | F88: 36.444.757/0003-83 | G88: BELO HORIZONTE | H88: MG | I88: (31) 3651-2088 | J88: MARCOS@CONSULFORTEBH.COM.BR | K88: PJ | L88: Ativo | M88: Sim
A89: 573 | B89: CEVAROLI SUPERMERCAD | C89: Cevaroli / OPA | D89: Supermercado | E89: CEVAROLI SUPERMERCADOS LTDA | F89: 36.444.757/0001-11 | G89: Belo Horizonte | H89: MG | I89: (31) 3433-3070 | J89: fiscal@supermercadosopa.com.br | K89: PJ | L89: Ativo | M89: Sim
A90: 482 | B90: CHIQUINHO SORVETES | C90: — | D90: Açaí | E90: MGK COMERCIO ALIMENTICIOS LTDA | F90: 24.920.519/0001-56 | G90: Governador Vala | H90: MG | I90: 33 9885 07007 | J90: governadorvaladares@chiquinho.com.br | K90: PJ | L90: Ativo | M90: —
A91: 484 | B91: CHIQUINHO SORVETES | C91: — | D91: Açaí | E91: GRENCHEN E KELTERN COMERCIO ALIMENTICIO LTDA | F91: 19.121.816/0001-00 | G91: Governador Vala | H91: MG | I91: 33 9885 07007 | J91: governadorvaladares@chiquinho.com.br | K91: PJ | L91: Ativo | M91: —
A92: 483 | B92: CHIQUINHO SORVETES | C92: — | D92: Açaí | E92: MELLO E MELLO COMERCIO ALIMENTICIOS LTDA | F92: 16.781.332/0001-90 | G92: Teofilo Otoni | H92: MG | I92: 33 9885 07007 | J92: governadorvaladares@chiquinho.com.br | K92: PJ | L92: Ativo | M92: —
A93: 456 | B93: CHIQUINHO SORVETES CENTRO | C93: — | D93: Açaí | E93: ALIMENTOS IPATINGA LTDA - ME | F93: 19.615.271/0001-80 | G93: IPATINGA | H93: MG | I93: 31 99418 1634 | J93: chiquinhoipatinga@gmail.com | K93: PJ | L93: Fechou | M93: —
A94: 389 | B94: CHISTE SORVETES LTDA | C94: — | D94: Açaí | E94: CHISTE SORVETES EIRELI - ME | F94: 13.910.462/0001-98 | G94: Governador Vala | H94: MG | I94: 33 99931 2603 | J94: VINICIUSCHISTE@HOTMAIL.COM | K94: PJ | L94: Inativo | M94: —
A95: 569 | B95: CIA DO CHURRASCO | C95: — | D95: Delicatese | E95: INACIO E SILVA COMERCIO DE ALIMENTOS EIRELI | F95: 23.800.181/0001-36 | G95: Ipatinga | H95: MG | I95: 31 3617 8968 | J95: nivaldodochurrasco@yahoo.com.br | K95: PJ | L95: Ativo | M95: —
A96: 634 | B96: CIRURGICA DINIZ | C96: — | D96: Distribuidor | E96: DINIZ DISTRIBUIDORA DE PRODUTOS HOSPITALARES E ODONTOLOGICOS LTDA | F96: 12.092.335/0001-66 | G96: Caratinga | H96: MG | I96: (33) 3321-3595 | J96: GENESECONTABIL@YAHOO.COM.BR | K96: PJ | L96: Inativo | M96: —
A97: 426 | B97: CISCA DISTRIBUIDORA | C97: — | D97: Distribuidor Açaí | E97: CISCA DISTRIBUIDORA LTDA ME | F97: 20.604.732/0001-06 | G97: Governador Vala | H97: MG | I97: 33 3063 3022 | J97: cisca.distribuidora@hotmail.com | K97: PJ | L97: Inativo | M97: Sim
A98: 726 | B98: CLEAN RESOLVE | C98: — | D98: — | E98: CLEAN RESOLVE LTDA | F98: 46.554.329/0001-03 | G98: SANTA MARGARIDA | H98: MG | I98: (33) 8429-5412 | J98: andrecarv85@gmail.com | K98: PJ | L98: Ativo | M98: —
A99: 774 | B99: Cliente Teste - SV.FUNIL | C99: — | D99: — | E99: Cliente Teste - SV.FUNIL | K99: PJ | L99: Ativo | M99: —
A100: 392 | B100: COELHO DINIZ LOJA 1 | C100: Coelho Diniz | D100: Supermercado | E100: SUPERMERCADO COELHO DINIZ EIRELI | F100: 41.930.199/0001-34 | G100: Governador Vala | H100: MG | I100: 33 3279 6100 | J100: nf01@coelhodiniz.com.br | K100: PJ | L100: Ativo | M100: Sim
A101: 401 | B101: COELHO DINIZ LOJA 10 | C101: Coelho Diniz | D101: Supermercado | E101: SUPERMERCADO COELHO DINIZ EIRELI | F101: 41.930.199/0010-25 | G101: Governador Vala | H101: MG | I101: 33 3279 6652 | J101: nf10@coelhodiniz.com.br | K101: PJ | L101: Ativo | M101: Sim
A102: 402 | B102: COELHO DINIZ LOJA 11 | C102: Coelho Diniz | D102: Supermercado | E102: SUPERMERCADO COELHO DINIZ EIRELI | F102: 41.930.199/0011-06 | G102: Governador Vala | H102: MG | I102: 33 3213 4200 | J102: nf11@coelhodiniz.com.br; portaria11@coelhodiniz.com.br | K102: PJ | L102: Ativo | M102: Sim
A103: 403 | B103: COELHO DINIZ LOJA 12 | C103: Coelho Diniz | D103: Supermercado | E103: SUPERMERCADO COELHO DINIZ EIRELI | F103: 41.930.199/0012-97 | G103: Coronel Fabrici | H103: MG | I103: 33 3865 2600 | J103: nf12@coelhodiniz.com.br | K103: PJ | L103: Ativo | M103: Sim
A104: 404 | B104: COELHO DINIZ LOJA 13 | C104: Coelho Diniz | D104: Supermercado | E104: SUPERMERCADO COELHO DINIZ EIRELI | F104: 41.930.199/0013-78 | G104: Ipatinga | H104: MG | I104: 31 3828 2700 | J104: nf13@coelhodiniz.com.br | K104: PJ | L104: Ativo | M104: Sim
A105: 405 | B105: COELHO DINIZ LOJA 14 | C105: Coelho Diniz | D105: Supermercado | E105: SUPERMERCADO COELHO DINIZ EIRELI | F105: 41.930.199/0014-59 | G105: Teofilo Otoni | H105: MG | I105: 33 3529 4150 | J105: nf14@coelhodiniz.com.br | K105: PJ | L105: Ativo | M105: Sim
A106: 406 | B106: COELHO DINIZ LOJA 15 | C106: Coelho Diniz | D106: Supermercado | E106: SUPERMERCADO COELHO DINIZ EIRELI | F106: 41.930.199/0015-30 | G106: Governador Vala | H106: MG | I106: 33 3213 5900 | J106: nf15@coelhodiniz.com.br | K106: PJ | L106: Ativo | M106: Sim
A107: 407 | B107: COELHO DINIZ LOJA 16 | C107: Coelho Diniz | D107: Supermercado | E107: SUPERMERCADO COELHO DINIZ EIRELI | F107: 41.930.199/0016-10 | G107: Teofilo Otoni | H107: MG | I107: 33 3536 0400 | J107: nf16@coelhodiniz.com.br | K107: PJ | L107: Ativo | M107: Sim
A108: 408 | B108: COELHO DINIZ LOJA 17 | C108: Coelho Diniz | D108: Supermercado | E108: SUPERMERCADO COELHO DINIZ EIRELI | F108: 41.930.199/0017-00 | G108: Ipatinga | H108: MG | I108: 31 3828 2300 | J108: nf17@coelhodiniz.com.br | K108: PJ | L108: Ativo | M108: Sim
A109: 409 | B109: COELHO DINIZ LOJA 18 | C109: Coelho Diniz | D109: Supermercado | E109: SUPERMERCADO COELHO DINIZ EIRELI | F109: 41.930.199/0018-82 | G109: Governador Vala | H109: MG | I109: 33 3212 9450 | J109: nf18@coelhodiniz.com.br | K109: PJ | L109: Ativo | M109: Sim
A110: 410 | B110: COELHO DINIZ LOJA 19 | C110: Coelho Diniz | D110: Supermercado | E110: SUPERMERCADO COELHO DINIZ EIRELI | F110: 41.930.199/0019-63 | G110: Caratinga | H110: MG | I110: 33 3322 7551 | J110: portaria19@coelhodiniz.com.br | K110: PJ | L110: Ativo | M110: Sim
A111: 393 | B111: COELHO DINIZ LOJA 2 | C111: Coelho Diniz | D111: Supermercado | E111: SUPERMERCADO COELHO DINIZ EIRELI | F111: 41.930.199/0002-15 | G111: Governador Vala | H111: MG | I111: 33 3279 6150 | J111: nf02@coelhodiniz.com.br | K111: PJ | L111: Ativo | M111: Sim
... A122: 624 | B122: COFARMINAS | C122: — | D122: Distribuidora Farma | E122: COFARMINAS COMERCIO DE PRODUTOS FARMACEUTICOS LTDA | F122: 02.537.890/0001-09 | G122: GOVERNADOR VALADARES | H122: MG | I122: (33) 3277-9200 | J122: GERENCIA@COFARMINAS.COM.BR | K122: PJ | L122: Inativo | M122: —
A123: 474 | B123: COMERCIAL FRAGA | C123: — | D123: Supermercado | E123: COMERCIAL FRAGA LTDA | F123: 71.216.113/0001-77 | G123: JOAO MONLEVADE | H123: MG | I123: 31 3852 5292 | K123: PJ | L123: Inativo | M123: —
A124: 920 | B124: COMERCIAL JOAO LUIZ FRIZZERA LTDA | C124: — | D124: — | E124: COMERCIAL JOAO LUIZ FRIZZERA LTDA | F124: 04.371.905/0001-29 | G124: Aimorés | H124: MG | K124: PJ | L124: Ativo | M124: Sim
A125: 643 | B125: COMERCIO & INDUSTRIA DE SORVETES LOUBACH | C125: — | D125: Distribuidor Açaí | E125: COMERCIO & INDUSTRIA DE SORVETES LOUBACH LTDA | F125: 09.029.595/0001-82 | G125: Governador Valadares | H125: MG | I125: (33) 3271-1995 | J125: PONTUAL@CONTABILIDADEPONTUAL.COM.BR | K125: PJ | L125: Inativo | M125: Sim
A126: 510 | B126: COMPRE CERTO SINHA | C126: — | D126: Supermercado | E126: SINHA FARMA EIRELI | F126: 18.383.640/0001-93 | G126: Uberlandia | H126: MG | I126: 34 99242 0085 | J126: sinhafarma@gmail.com | K126: PJ | L126: Ativo | M126: —
...

Sheet Evolução Anual
A1: Cliente | B1: Grupo/Rede | C1: Canal | D1: Cidade | E1: UF | F1: 2023 | G1: 2024 | H1: 2025 | I1: 2026 | J1: Total 4 anos | K1: % 24/23 | L1: % 25/24 | M1: % 26/25
A2: 3MV REPRESENTACOES | B2: — | C2: Representações | D2: IPATINGA | E2: MG | F2: 0 | G2: 3992.5898 | H2: 0 | I2: 0 | J2: 3992.5898 | K2: 🆕 novo | L2: -1 | M2: —
A3: ACAI & CIA | B3: — | C3: Açaí | D3: GOVERNADOR VALADARES | E3: MG | F3: 34140.306 | G3: 37812.749 | H3: 36111.976 | I3: 16822.989 | J3: 124888.02 | K3: 0.10756914 | L3: -0.04497882 | M3: -0.53414376
A4: ACAI FRUIT SHOW COLATINA | B4: — | C4: — | D4: COLATINA | E4: ES | F4: 4976.16 | G4: 1658.72 | H4: 0 | I4: 0 | J4: 6634.88 | K4: -0.66666667 | L4: -1 | M4: —
A5: ACAI FRUIT SHOW GV | B5: — | C5: Açaí | D5: GOVERNADOR VALA | E5: MG | F5: 2101.4587 | G5: 272.59878 | H5: 0 | I5: 0 | J5: 2374.0575 | K5: -0.87028116 | L5: -1 | M5: —
A6: ACAI FRUIT SHOW IPATINGA | B6: — | C6: Açaí | D6: IPATINGA | E6: MG | F6: 1848.6928 | G6: 272.59878 | H6: 0 | I6: 0 | J6: 2121.2916 | K6: -0.85254512 | L6: -1 | M6: —
A7: ACAI FRUIT SHOW TEOFILO OTONI | B7: — | C7: Açaí | D7: TEOFILO OTONI | E7: MG | F7: 2797.5542 | G7: 259.59926 | H7: 0 | I7: 0 | J7: 3057.1535 | K7: -0.90720492 | L7: -1 | M7: —
A8: ACAI FRUIT SHOW TIMOTEO | B8: — | C8: Açaí | D8: TIMOTEO | E8: MG | F8: 2061.7929 | G8: 272.59878 | H8: 0 | I8: 0 | J8: 2334.3917 | K8: -0.86778557 | L8: -1 | M8: —
A9: ACAI NO KILO GOVERNADOR VALADARES | B9: — | C9: — | D9: Governador Valadares | E9: MG | F9: 1071.3905 | G9: 960.99814 | H9: 0 | I9: 0 | J9: 2032.3887 | K9: -0.10303655 | L9: -1 | M9: —
A10: ALISSON DE BRITO LITTIG | B10: — | C10: — | D10: Governador Valadares | E10: MG | F10: 1467.9941 | G10: 0 | H10: 0 | I10: 0 | J10: 1467.9941 | K10: -1 | L10: — | M10: —
A11: ALOE BAF | B11: — | C11: Distribuidor | D11: MONTES CLAROS | E11: MG | F11: 837944.95 | G11: 1645728.5 | H11: 1500020.4 | I11: 181545.09 | J11: 4165238.9 | K11: 0.96400547 | L11: -0.088537096 | M11: -0.87897159
A12: ANDRADE DISTRIBUIDORA | B12: Andrade Distribuidora | C12: Distribuidor | D12: IPATINGA | E12: MG | F12: 14356.014 | G12: 25928.647 | H12: 30166.824 | I12: 6618.577 | J12: 77070.062 | K12: 0.8061174 | L12: 0.16345537 | M12: -0.7806008
A13: ARAUJO E AMORIM | B13: — | C13: Açaí | D13: CARATINGA | E13: MG | F13: 673.14506 | G13: 768.26013 | H13: 0 | I13: 0 | J13: 1441.4052 | K13: 0.14129951 | L13: -1 | M13: —
A14: ARMAZEM DO ACAI | B14: — | C14: Açaí | D14: GOVERNADOR VALA | E14: MG | F14: 3171.4112 | G14: 2233.237 | H14: 2877.0239 | I14: 1233.0102 | J14: 9514.6823 | K14: -0.29582232 | L14: 0.2882752 | M14: -0.57142857
A15: ATACADO SANTA MARIA | B15: — | C15: Atacarejo | D15: SANTA MARIA DE | E15: MG | F15: 21884.029 | G15: 42112.801 | H15: 25961.341 | I15: 0 | J15: 89958.171 | K15: 0.92436231 | L15: -0.38352851 | M15: -1
A16: ATACADÃO S. FURTADO 02 | B16: S. Furtado | C16: Atacado | D16: IPANEMA | E16: MG | F16: 168413.17 | G16: 247194.37 | H16: 240077.51 | I16: 24131.084 | J16: 679816.13 | K16: 0.46778527 | L16: -0.028790521 | M16: -0.89948628
A17: ATACAREJO SAMPAIO MANTENOPOLIS | B17: — | C17: Supermercado | D17: Mantenópolis | E17: ES | F17: 143985.72 | G17: 0 | H17: 0 | I17: 0 | J17: 143985.72 | K17: -1 | L17: — | M17: —
A18: ATACAREJO SAO JOAO - ABRE CAMPO | B18: São João / Gardingo | C18: — | D18: Abre Campo | E18: MG | F18: 0 | G18: 1872.6666 | H18: 3115.2703 | I18: 2163.3974 | J18: 7151.3344 | K18: 🆕 novo | L18: 0.66354774 | M18: -0.30555065
A19: ATACAREJO SÃO JOAO | B19: São João / Gardingo | C19: Atacarejo | D19: MATIPO | E19: MG | F19: 6870.7551 | G19: 9845.6677 | H19: 7521.6446 | I19: 2216.359 | J19: 26454.426 | K19: 0.4329819 | L19: -0.23604525 | M19: -0.70533586
A20: BEAUTY CENTER | B20: — | C20: — | D20: Nanuque | E20: MG | F20: 0 | G20: 6647.1411 | H20: 0 | I20: 0 | J20: 6647.1411 | K20: 🆕 novo | L20: -1 | M20: —
A21: BELEZA & CIA | B21: — | C21: Perfumaria | D21: Governador Valadares | E21: MG | F21: 3329.3978 | G21: 0 | H21: 0 | I21: 0 | J21: 3329.3978 | K21: -1 | L21: — | M21: —
A22: BELLACENTER DISTRIBUIDORA | B22: — | C22: Distribuidor | D22: Uberaba | E22: MG | F22: 15060.88 | G22: 0 | H22: 0 | I22: 0 | J22: 15060.88 | K22: -1 | L22: — | M22: —
A23: BIG MAIS SUPERMERCAD | B23: Big Mais | C23: Supermercado | D23: Governador Vala | E23: MG | F23: 462731.89 | G23: 477033.78 | H23: 826779.81 | I23: 246423.43 | J23: 2012968.9 | K23: 0.030907518 | L23: 0.73316826 | M23: -0.70194793
A24: BIG PLUS SUPERMERCADO | B24: — | C24: — | D24: Timóteo | E24: MG | F24: 0 | G24: 1162.0754 | H24: 0 | I24: 0 | J24: 1162.0754 | K24: 🆕 novo | L24: -1 | M24: —
A25: BIOFLORA JANAUBA | B25: — | C25: — | D25: Janaúba | E25: MG | F25: 0 | G25: 0 | H25: 5461.8127 | I25: 0 | J25: 5461.8127 | K25: — | L25: 🆕 novo | M25: -1
A26: BRASIL SUPERMERCADOS CIDADE NOBRE | B26: Supermercado Brasil | C26: Supermercado | D26: IPATINGA | E26: MG | F26: 19324.073 | G26: 24674.992 | H26: 16107.027 | I26: 0 | J26: 60106.092 | K26: 0.27690431 | L26: -0.34723274 | M26: -1
A27: BRASIL SUPERMERCADOS PANORAMA | B27: Supermercado Brasil | C27: Supermercado | D27: IPATINGA | E27: MG | F27: 26092.83 | G27: 17852.688 | H27: 11013.518 | I27: 0 | J27: 54959.035 | K27: -0.31580103 | L27: -0.38308909 | M27: -1
A28: BRASIL SUPERMERCADOS TIMOTEO | B28: Supermercado Brasil | C28: Supermercado | D28: TIMOTEO | E28: MG | F28: 34961.442 | G28: 31148.195 | H28: 18225.334 | I28: 0 | J28: 84334.971 | K28: -0.10907007 | L28: -0.41488315 | M28: -1
A29: C BAESSA DISTRIBUIDORA | B29: — | C29: Atacado | D29: SANTANA DO MANHUACU | E29: MG | F29: 47206.729 | G29: 76115.913 | H29: 0 | I29: 0 | J29: 123322.64 | K29: 0.6123954 | L29: -1 | M29: —
A30: CABELO & CIA CARATINGA | B30: — | C30: — | D30: Caratinga | E30: MG | F30: 2972.408 | G30: 8271.4643 | H30: 0 | I30: 0 | J30: 11243.872 | K30: 1.7827486 | L30: -1 | M30: —
A31: CABELO & CIA PRODUTOS PARA CABELOS EIRELI | B31: — | C31: Perfumaria | D31: GOVERNADOR VALADARES | E31: MG | F31: 3755.4457 | G31: 4453.8347 | H31: 6990.6837 | I31: 0 | J31: 15199.964 | K31: 0.18596699 | L31: 0.5695876 | M31: -1
A32: CABELO & PELE | B32: — | C32: Perfumaria | D32: Governador Valadares | E32: MG | F32: 8068.3901 | G32: 4218.9298 | H32: 0 | I32: 0 | J32: 12287.32 | K32: -0.47710389 | L32: -1 | M32: —
A33: CASA ALADIM BA | B33: — | C33: Distribuidor | D33: Feira de Santana | E33: BA | F33: 8863488.5 | G33: 6680272.2 | H33: 2737709.5 | I33: 407506.12 | J33: 18688976 | K33: -0.24631569 | L33: -0.59017995 | M33: -0.85115071
A34: CASA ALADIM BETIM MG | B34: — | C34: — | D34: Betim | E34: MG | F34: 4447040.7 | G34: 4876191 | H34: 1029083.5 | I34: 552701.64 | J34: 10905017 | K34: 0.096502446 | L34: -0.7889575 | M34: -0.46291858
A35: CASA ALADIM MG | B35: — | C35: Distribuidor | D35: TEÓFILO OTONI | E35: MG | F35: 709262.99 | G35: 695847.86 | H35: 185185.98 | I35: 0 | J35: 1590296.8 | K35: -0.018914174 | L35: -0.73387001 | M35: -1
A36: CASA DO BISCOITO | B36: — | C36: — | D36: Manhuaçu | E36: MG | F36: 5530.1242 | G36: 0 | H36: 0 | I36: 0 | J36: 5530.1242 | K36: -1 | L36: — | M36: —
A37: CASA DO BISCOITO DE CARATINGA | B37: — | C37: — | D37: Caratinga | E37: MG | F37: 5530.1242 | G37: 0 | H37: 0 | I37: 0 | J37: 5530.1242 | K37: -1 | L37: — | M37: —
A38: CASA DO CABELEIREIRO DE CARATINGA | B38: — | C38: — | D38: Caratinga | E38: MG | F38: 0 | G38: 4190.3126 | H38: 0 | I38: 0 | J38: 4190.3126 | K38: 🆕 novo | L38: -1 | M38: —
A39: CASA PINHO | B39: — | C39: — | D39: Sabinópolis | E39: MG | F39: 4793.8662 | G39: 0 | H39: 0 | I39: 0 | J39: 4793.8662 | K39: -1 | L39: — | M39: —
A40: CD GARCIA JARDIM PANORAMA | B40: Garcia Supermercados | C40: — | D40: Ipatinga | E40: MG | F40: 0 | G40: 0 | H40: 151605.18 | I40: 0 | J40: 151605.18 | K40: — | L40: 🆕 novo | M40: -1
A41: CENTRAL SUPERMERCADOS | B41: — | C41: Supermercado | D41: Conselheiro Pena | E41: MG | F41: 21704.38 | G41: 0 | H41: 0 | I41: 0 | J41: 21704.38 | K41: -1 | L41: — | M41: —
A42: CEVAROLI FILIAL | B42: Cevaroli / OPA | C42: Supermercado | D42: BELO HORIZONTE | E42: MG | F42: 34481.901 | G42: 27123.747 | H42: 20439.083 | I42: 4221.1879 | J42: 86265.918 | K42: -0.21339178 | L42: -0.24645061 | M42: -0.79347469
A43: CEVAROLI SUPERMERCAD | B43: Cevaroli / OPA | C43: Supermercado | D43: Belo Horizonte | E43: MG | F43: 47577.558 | G43: 31161.361 | H43: 25316.349 | I43: 4290.37 | J43: 108345.64 | K43: -0.34504078 | L43: -0.1875724 | M43: -0.83052967
A44: CISCA DISTRIBUIDORA | B44: — | C44: Distribuidor Açaí | D44: Governador Vala | E44: MG | F44: 15612.769 | G44: 5189.6845 | H44: 5941.816 | I44: 0 | J44: 26744.269 | K44: -0.66759999 | L44: 0.14492818 | M44: -1
A45: COELHO DINIZ LOJA 1 | B45: Coelho Diniz | C45: Supermercado | D45: Governador Vala | E45: MG | F45: 5276.7288 | G45: 19091.411 | H45: 19346.719 | I45: 685.94029 | J45: 44400.799 | K45: 2.6180391 | L45: 0.013372936 | M45: -0.96454488
A46: COELHO DINIZ LOJA 10 | B46: Coelho Diniz | C46: Supermercado | D46: Governador Vala | E46: MG | F46: 11051.492 | G46: 9248.31 | H46: 66001.598 | I46: 12962.978 | J46: 99264.378 | K46: -0.16316189 | L46: 6.1366118 | M46: -0.803596
A47: COELHO DINIZ LOJA 11 | B47: Coelho Diniz | C47: Supermercado | D47: Governador Vala | E47: MG | F47: 6445.332 | G47: 3759.51 | H47: 18622.992 | I47: 3576.5516 | J47: 32404.386 | K47: -0.41670809 | L47: 3.9535689 | M47: -0.80794967
A48: COELHO DINIZ LOJA 12 | B48: Coelho Diniz | C48: Supermercado | D48: Coronel Fabrici | E48: MG | F48: 27161.766 | G48: 39769.322 | H48: 91065.126 | I48: 27195.207 | J48: 185191.42 | K48: 0.46416553 | L48: 1.2898335 | M48: -0.7013653
A49: COELHO DINIZ LOJA 13 | B49: Coelho Diniz | C49: Supermercado | D49: Ipatinga | E49: MG | F49: 9823.8744 | G49: 36685.292 | H49: 75199.55 | I49: 23852.754 | J49: 145561.47 | K49: 2.7342997 | L49: 1.0498556 | M49: -0.68280722
A50: COELHO DINIZ LOJA 14 | B50: Coelho Diniz | C50: Supermercado | D50: Teofilo Otoni | E50: MG | F50: 12911.771 | G50: 26428.774 | H50: 64239.541 | I50: 20530.551 | J50: 124110.64 | K50: 1.0468745 | L50: 1.4306667 | M50: -0.68040632
A51: COELHO DINIZ LOJA 15 | B51: Coelho Diniz | C51: Supermercado | D51: Governador Vala | E51: MG | F51: 10309.403 | G51: 33533.218 | H51: 68838.267 | I51: 17650.491 | J51: 130331.38 | K51: 2.2526828 | L51: 1.0528381 | M51: -0.74359478
A52: COELHO DINIZ LOJA 16 | B52: Coelho Diniz | C52: Supermercado | D52: Teofilo Otoni | E52: MG | F52: 3364.92 | G52: 2543.67 | H52: 90503.499 | I52: 24301.518 | J52: 120713.61 | K52: -0.24406227 | L52: 34.57989 | M52: -0.73148532
A53: COELHO DINIZ LOJA 17 | B53: Coelho Diniz | C53: Supermercado | D53: Ipatinga | E53: MG | F53: 18198.439 | G53: 30932.762 | H53: 105473.44 | I53: 26049.733 | J53: 180654.37 | K53: 0.69974805 | L53: 2.4097646 | M53: -0.75302091
... A57: COELHO DINIZ LOJA 20 | B57: Coelho Diniz | C57: Supermercado | D57: Manhuacu | E57: MG | F57: 13603.378 | G57: 43973.552 | H57: 127389.8 | I57: 24117.796 | J57: 209084.53 | K57: 2.2325466 | L57: 1.8969641 | M57: -0.81067718
A58: COELHO DINIZ LOJA 21 | B58: Coelho Diniz | C58: Supermercado | D58: Governador Vala | E58: MG | F58: 0 | G58: 0 | H58: 0 | I58: 74702.863 | J58: 74702.863 | K58: — | L58: — | M58: 🆕 novo
A59: COELHO DINIZ LOJA 22 | B59: Coelho Diniz | C59: Supermercado | D59: Ipatinga | E59: MG | F59: 13736.138 | G59: 21111.929 | H59: 81937.461 | I59: 7363.4223 | J59: 124148.95 | K59: 0.53696243 | L59: 2.8810978 | M59: -0.91013363
A60: COELHO DINIZ LOJA 3 | B60: Coelho Diniz | C60: Supermercado | D60: Governador Vala | E60: MG | F60: 10027.638 | G60: 27354.196 | H60: 42834.007 | I60: 13740.866 | J60: 93956.707 | K60: 1.7278803 | L60: 0.56590263 | M60: -0.67920663
A61: COELHO DINIZ LOJA 4 | B61: Coelho Diniz | C61: Supermercado | D61: Manhuacu | E61: MG | F61: 14346.778 | G61: 7375.23 | H61: 86890.394 | I61: 10521.429 | J61: 119133.83 | K61: -0.48593125 | L61: 10.781381 | M61: -0.87891148
A62: COELHO DINIZ LOJA 5 | B62: Coelho Diniz | C62: Supermercado | D62: Governador Vala | E62: MG | F62: 4665.4488 | G62: 3279.57 | H62: 10785.046 | I62: 0 | J62: 18730.065 | K62: -0.29705155 | L62: 2.2885548 | M62: -1
A63: COELHO DINIZ LOJA 6 | B63: Coelho Diniz | C63: Supermercado | D63: Governador Vala | E63: MG | F63: 25256.66 | G63: 10512 | H63: 91170.565 | I63: 22927.493 | J63: 149866.72 | K63: -0.58379295 | L63: 7.6729989 | M63: -0.74852088
A64: COELHO DINIZ LOJA 7 | B64: Coelho Diniz | C64: Supermercado | D64: Caratinga | E64: MG | F64: 8420.4828 | G64: 19695.731 | H64: 46560.131 | I64: 6816.5034 | J64: 81492.849 | K64: 1.3390264 | L64: 1.3639707 | M64: -0.85359785
A65: COELHO DINIZ LOJA 8 | B65: Coelho Diniz | C65: Supermercado | D65: GOVERNADOR VALA | E65: MG | F65: 0 | G65: 499129.94 | H65: 291004.88 | I65: 0 | J65: 790134.81 | K65: 🆕 novo | L65: -0.41697571 | M65: -1
A66: COELHO DINIZ LOJA 9 | B66: Coelho Diniz | C66: Supermercado | D66: Governador Valadares | E66: MG | F66: 29533.032 | G66: 41764.172 | H66: 63287.89 | I66: 18816.405 | J66: 153401.5 | K66: 0.41415116 | L66: 0.51536322 | M66: -0.70268554
A67: COMERCIAL JOAO LUIZ FRIZZERA LTDA | B67: — | C67: — | D67: Aimorés | E67: MG | F67: 0 | G67: 0 | H67: 0 | I67: 8863.3251 | J67: 8863.3251 | K67: — | L67: — | M67: 🆕 novo
A68: COMERCIO & INDUSTRIA DE SORVETES LOUBACH | B68: — | C68: Distribuidor Açaí | D68: Governador Valadares | E68: MG | F68: 5385.1604 | G68: 0 | H68: 0 | I68: 0 | J68: 5385.1604 | K68: -1 | L68: — | M68: —
A69: CONSUL | B69: Consul Supermercados | C69: — | D69: Ipatinga | E69: MG | F69: 0 | G69: 74195.545 | H69: 51568.292 | I69: 11689.382 | J69: 137453.22 | K69: 🆕 novo | L69: -0.3049678 | M69: -0.7733223
A70: CONSUL BOM RETIRO | B70: Consul Supermercados | C70: Supermercado | D70: IPATINGA | E70: MG | F70: 23004.372 | G70: 23981.259 | H70: 65154.515 | I70: 10408.281 | J70: 122548.43 | K70: 0.042465266 | L70: 1.716893 | M70: -0.84025234
A71: CONSUL CIDADE NOVA | B71: Consul Supermercados | C71: — | D71: Santana do Paraíso | E71: MG | F71: 0 | G71: 1714.74 | H71: 8513.2178 | I71: 0 | J71: 10227.958 | K71: 🆕 novo | L71: 3.9647281 | M71: -1
A72: CONSUL HORTO | B72: Consul Supermercados | C72: — | D72: Ipatinga | E72: MG | F72: 3825.6552 | G72: 3487.41 | H72: 8580.4888 | I72: 2051.849 | J72: 17945.403 | K72: -0.088414973 | L72: 1.4604187 | M72: -0.76087039
A73: CONSUL IGUAÇU | B73: Consul Supermercados | C73: Supermercado | D73: Ipatinga | E73: MG | F73: 3213.1362 | G73: 8946.7004 | H73: 28875.347 | I73: 2806.3104 | J73: 43841.494 | K73: 1.7844137 | L73: 2.2274857 | M73: -0.90281293
A74: CONSUL SUPERMERCADO QUITANDINHA | B74: Consul Supermercados | C74: Supermercado | D74: Timoteo | E74: MG | F74: 17088.211 | G74: 27757.778 | H74: 48109.364 | I74: 9988.0321 | J74: 102943.38 | K74: 0.62438174 | L74: 0.733185 | M74: -0.79238902
A75: CONSUL SUPERMERCADOS CARIRU | B75: Consul Supermercados | C75: Supermercado | D75: Ipatinga | E75: MG | F75: 38648.923 | G75: 30098.74 | H75: 74288.401 | I75: 12527.125 | J75: 155563.19 | K75: -0.22122694 | L75: 1.4681565 | M75: -0.83137172
A76: CONSUL SUPERMERCADOS IDEAL | B76: Consul Supermercados | C76: Supermercado | D76: Ipatinga | E76: MG | F76: 10548.367 | G76: 16953.089 | H76: 39757.055 | I76: 9686.4036 | J76: 76944.915 | K76: 0.60717665 | L76: 1.3451216 | M76: -0.75636013
A77: CONSUL SUPERMERCADOS INDUSTRIAL | B77: Consul Supermercados | C77: Supermercado | D77: Ipatinga | E77: MG | F77: 0 | G77: 0 | H77: 2065.52 | I77: 1549.83 | J77: 3615.35 | K77: — | L77: 🆕 novo | M77: -0.24966594
A78: CONSUL VENEZA | B78: Consul Supermercados | C78: Supermercado | D78: Ipatinga | E78: MG | F78: 799.20589 | G78: 3330.6231 | H78: 11629.726 | I78: 2181.7738 | J78: 17941.328 | K78: 3.1674156 | L78: 2.4917568 | M78: -0.8123968
A79: CORDEIRO ATACAREJO - AV ANTONIO ERNESTO CURVELO | B79: Cordeiro Supermercados | C79: — | D79: Curvelo | E79: MG | F79: 0 | G79: 0 | H79: 11119.267 | I79: 9002.0693 | J79: 20121.336 | K79: — | L79: 🆕 novo | M79: -0.19040803
A80: CORDEIRO ATACAREJO - AV FLORIPES SALINAS | B80: Cordeiro Supermercados | C80: — | D80: Salinas | E80: MG | F80: 0 | G80: 0 | H80: 13536.068 | I80: 14567.274 | J80: 28103.342 | K80: — | L80: 🆕 novo | M80: 0.076182026
A81: CORDEIRO ATACAREJO - CAPELINHA | B81: Cordeiro Supermercados | C81: — | D81: Capelinha | E81: MG | F81: 0 | G81: 0 | H81: 5282.7854 | I81: 1940.519 | J81: 7223.3045 | K81: — | L81: 🆕 novo | M81: -0.63267124
A82: CORDEIRO ATACAREJO - ITAMARANDIBA | B82: Cordeiro Supermercados | C82: — | D82: Itamarandiba | E82: MG | F82: 0 | G82: 0 | H82: 9006.3173 | I82: 11677.847 | J82: 20684.164 | K82: — | L82: 🆕 novo | M82: 0.29662843
A83: CORDEIRO ATACAREJO - JARDIM PALMEIRAS MONTES CLAROS | B83: Cordeiro Supermercados | C83: — | D83: Montes Claros | E83: MG | F83: 0 | G83: 0 | H83: 7148.0827 | I83: 9050.1142 | J83: 16198.197 | K83: — | L83: 🆕 novo | M83: 0.26608974
A84: CORDEIRO ATACAREJO - PEDRA GRANDE DIAMANTINA | B84: Cordeiro Supermercados | C84: — | D84: Diamantina | E84: MG | F84: 0 | G84: 0 | H84: 9003.8638 | I84: 13686.399 | J84: 22690.263 | K84: — | L84: 🆕 novo | M84: 0.52005847
A85: CORDEIRO ATACAREJO - PLANALTO MONTES CLAROS | B85: Cordeiro Supermercados | C85: — | D85: Montes Claros | E85: MG | F85: 0 | G85: 0 | H85: 5575.4314 | I85: 10106.466 | J85: 15681.897 | K85: — | L85: 🆕 novo | M85: 0.81267867
A86: CORDEIRO ATACAREJO - RUA DOS IPES ARAÇUAI | B86: Cordeiro Supermercados | C86: — | D86: Araçuaí | E86: MG | F86: 0 | G86: 0 | H86: 12797.217 | I86: 16634.263 | J86: 29431.48 | K86: — | L86: 🆕 novo | M86: 0.29983441
A87: CORDEIRO SUPERMERCADOS - AV JOAO ANTUNES DIAMANTINA | B87: Cordeiro Supermercados | C87: — | D87: Diamantina | E87: MG | F87: 0 | G87: 0 | H87: 10716.438 | I87: 9062.7734 | J87: 19779.211 | K87: — | L87: 🆕 novo | M87: -0.15431103
A88: CORDEIRO SUPERMERCADOS - BAIRRO RAQUEL SALINAS | B88: Cordeiro Supermercados | C88: — | D88: Salinas | E88: MG | F88: 0 | G88: 0 | H88: 5783.8402 | I88: 8587.8581 | J88: 14371.698 | K88: — | L88: 🆕 novo | M88: 0.48480211
A89: CORDEIRO SUPERMERCADOS - BOCAIUVA | B89: Cordeiro Supermercados | C89: — | D89: Bocaiúva | E89: MG | F89: 0 | G89: 0 | H89: 8452.8905 | I89: 7534.9058 | J89: 15987.796 | K89: — | L89: 🆕 novo | M89: -0.10860009
A90: CORDEIRO SUPERMERCADOS - CENTRO CURVELO | B90: Cordeiro Supermercados | C90: — | D90: Curvelo | E90: MG | F90: 0 | G90: 0 | H90: 6823.2394 | I90: 15437.944 | J90: 22261.183 | K90: — | L90: 🆕 novo | M90: 1.2625535
... A97: CORDEIRO SUPERMERCADOS - TAIOBEIRAS | B97: Cordeiro Supermercados | C97: — | D97: Taiobeiras | E97: MG | F97: 0 | G97: 0 | H97: 8316.5162 | I97: 7289.7732 | J97: 15606.289 | K97: — | L97: 🆕 novo | M97: -0.12345831
A98: CORDEIRO SUPERMERCADOS CD | B98: Cordeiro Supermercados | C98: Supermercado | D98: CURVELO | E98: MG | F98: 0 | G98: 170246.55 | H98: 606142.34 | I98: 0 | J98: 776388.89 | K98: 🆕 novo | L98: 2.5603796 | M98: -1
A99: COSMETICOS DE ITABIRA | B99: — | C99: Perfumaria | D99: Itabira | E99: MG | F99: 1362.9016 | G99: 0 | H99: 0 | I99: 0 | J99: 1362.9016 | K99: -1 | L99: — | M99: —
A100: COSMETICOS E CIA | B100: — | C100: Perfumaria | D100: CORONEL FABRICIANO | F100: 0 | G100: 1276.9296 | H100: 0 | I100: 0 | J100: 1276.9296 | K100: 🆕 novo | L100: -1 | M100: —
A101: CROLL | B101: — | C101: Atacado | D101: IPATINGA | E101: MG | F101: 51075.062 | G101: 127931.74 | H101: 128314.58 | I101: 29643.612 | J101: 336964.99 | K101: 1.504779 | L101: 0.0029924787 | M101: -0.76897705
A102: DCA CENTRO OESTE LTDA | B102: — | C102: — | D102: Aparecida de Goiânia | E102: GO | F102: 0 | G102: 2654934.3 | H102: 682342.82 | I102: 240986 | J102: 3578263.1 | K102: 🆕 novo | L102: -0.7429907 | M102: -0.64682562
A103: DECK ACAI | B103: — | C103: Açaí | D103: Governador Vala | E103: MG | F103: 4326.1482 | G103: 2453.3891 | H103: 2445.7734 | I103: 932.4107 | J103: 10157.721 | K103: -0.43289298 | L103: -0.0031041347 | M103: -0.61876652
A104: DENERBRAND RODRIGUES DE SOUZA | B104: — | C104: — | D104: Santana do Manhuaçu | E104: MG | F104: 0 | G104: 0 | H104: 1653.6543 | I104: 0 | J104: 1653.6543 | K104: — | L104: 🆕 novo | M104: -1
A105: DIBISA ATACADO | B105: — | C105: Atacado | D105: Joao Monlevade | E105: MG | F105: 12324.902 | G105: 11554.596 | H105: 0 | I105: 0 | J105: 23879.498 | K105: -0.0625 | L105: -1 | M105: —
A106: DINIZ LJ 23 | B106: Coelho Diniz | C106: Supermercado | D106: Timóteo | E106: MG | F106: 2993.13 | G106: 42091.502 | H106: 118466.25 | I106: 32746.156 | J106: 196297.04 | K106: 13.062704 | L106: 1.8144934 | M106: -0.72358241
A107: DINIZ LOJA 24 | B107: Coelho Diniz | C107: Supermercado | E107: MG | F107: 16087.226 | G107: 28005.866 | H107: 88869.856 | I107: 20808.597 | J107: 153771.55 | K107: 0.74087597 | L107: 2.1732587 | M107: -0.76585315
A108: DISTRI. GARDINGO | B108: São João / Gardingo | C108: Distribuidor | D108: MATIPO | E108: MG | F108: 611524.1 | G108: 203780.93 | H108: 85977.082 | I108: 27553.754 | J108: 928835.86 | K108: -0.6667655 | L108: -0.57809063 | M108: -0.6795221
A109: DISTRIBUIDORA DE COSMETICOS BARAO | B109: — | C109: Perfumaria | D109: Barão de Cocais | E109: MG | F109: 7644.7543 | G109: 17916.138 | H109: 2333.3975 | I109: 0 | J109: 27894.29 | K109: 1.3435859 | L109: -0.86976002 | M109: -1
...

Sheet Contatos Adicionais
A1: Indústria | B1: Setor | C1: Contato | D1: Cargo / Função | E1: E-mail | F1: Telefone / Celular | G1: Observações

Sheet _Listas
A1: Setores | B1: Indústrias | C1: Clientes
A2: Financeiro | B2: BR Spice | C2: .com açai
A3: Contas a Pagar | B3: Casa Madeia | C3: 3MV REPRESENTACOES
A4: Contas a Receber | B4: Condor | C4: A GRANEL
A5: Marketing | B5: Dana | C5: ACAI & CIA
A6: ADM | B6: Domno | C6: ACAI CAFE
A7: Gerência | B7: JACQUES JANINE | C7: ACAI CULTURA
A8: Supervisão | B8: Kanitz | C8: ACAI DICASA
A9: Trocas | B9: Leopoldina | C9: ACAI DO ARITANA
A10: NFD | B10: M Dias | C10: ACAI DO SIRLEI
A11: Encarte | B11: Melbras | C11: ACAI DOS VALES
B12: Ruby Rose | C12: ACAI FRUIT SHOW COLATINA
B13: Semina | C13: ACAI FRUIT SHOW GV
B14: Tia Sonia | C14: ACAI FRUIT SHOW IPATINGA
B15: Upper | C15: ACAI FRUIT SHOW TEOFILO OTONI
B16: Valduga | C16: ACAI FRUIT SHOW TIMOTEO
C17: ACAI FRUIT SHOW UBERLANDIA
C18: ACAI IPITANGA
C19: ACAI MIX BRASIL
C20: ACAI NO KILO GOVERNADOR VALADARES
C21: ACAI VIP
C22: ACAIDERA MIX
C23: ALCATEIA HAMBURGUERI
C24: ALIMENTOS NOBRE
C25: ALISSON DE BRITO LITTIG
C26: ALOE BAF
C27: ALVIM DISTRIBUIDORA
C28: AMARETTO IPATINGA
... C481: ZARB DISTRIBUIDORA
